{
  "treatments": [
    {
      "treatmentCode": "AAA131",
      "patient": "Lakshmi Sonja",
      "treatmentDate": "2021-08-31T07:19:53"
    },
    {
      "treatmentCode": "AA13134BA",
      "patient": "Judith Militsa",
      "treatmentDate": "2021-08-05T15:19:53"
    },
    {
      "treatmentCode": "A12B34C1CC",
      "patient": "Lakshmi Sonja",
      "treatmentDate": "2021-08-01T18:19:53"
    },
    {
      "treatmentCode": "A12B12AAA",
      "patient": "Chikondi Ieuan",
      "treatmentDate": "2021-07-31T07:19:53"
    },
    {
      "treatmentCode": "AAB123BB",
      "patient": "Zarina Raganhildis",
      "treatmentDate": "2020-08-31T07:19:53"
    },
    {
      "treatmentCode": "ABB1121BA",
      "patient": "Lawrence Akiko",
      "treatmentDate": "2021-06-31T07:19:53"
    },
    {
      "treatmentCode": "222BBAA",
      "patient": "Lawrence Akiko",
      "treatmentDate": "2021-06-31T09:19:53"
    },
    {
      "treatmentCode": "QW-12AAB22",
      "patient": "Perdita Chedomir",
      "treatmentDate": "2021-04-29T07:19:53"
    },
    {
      "treatmentCode": "23333AA",
      "patient": "Lakshmi Sonja",
      "treatmentDate": "2021-01-31T07:19:53"
    },
    {
      "treatmentCode": "122AQP2",
      "patient": "Valkyrie Chris",
      "treatmentDate": "2020-08-31T07:19:53"
    }
  ]
}
